Check_Chromedriver/Check_Chromedriver.py
Check_Chromedriver/__init__.py
Check_Chromedriver/libs/__init__.py
Check_Chromedriver/libs/deal_parse.py
Check_Chromedriver/libs/deal_reg.py
Check_Chromedriver/libs/deal_txt.py
Check_Chromedriver/libs/deal_zip.py
check_chromedriver-2.0.26.dist-info/METADATA
check_chromedriver-2.0.26.dist-info/WHEEL
check_chromedriver-2.0.26.dist-info/top_level.txt
check_chromedriver-2.0.26.dist-info/RECORD
