Metadata-Version: 2.1
Name: check-chromedriver
Version: 2.0.26
Summary: Check and update chromedriver for selenium automatically
Home-page: https://github.com/cuzai/Check_Chromedriver.git
Author: cuzai
Author-email: cuzai@naver.com
License: UNKNOWN
Keywords: selenium chromdriver auto download
Platform: UNKNOWN
Requires-Python: >=3
Requires-Dist: bs4
Requires-Dist: requests
